quantSim/__init__.py
quantSim/error.py
quantSim/gate.py
quantSim/gateContainer.py
quantSim/permute.py
quantSim/sim.py
quantSim/subGate.py
quantSim-0.1.1.dist-info/METADATA
quantSim-0.1.1.dist-info/WHEEL
quantSim-0.1.1.dist-info/top_level.txt
quantSim-0.1.1.dist-info/RECORD
